google_pandas_load/__init__.py
google_pandas_load/constants.py
google_pandas_load/load_config.py
google_pandas_load/loader.py
google_pandas_load/loader_quick_setup.py
google_pandas_load/utils.py
google_pandas_load-6.0.0.dist-info/LICENSE
google_pandas_load-6.0.0.dist-info/METADATA
google_pandas_load-6.0.0.dist-info/WHEEL
google_pandas_load-6.0.0.dist-info/top_level.txt
google_pandas_load-6.0.0.dist-info/RECORD
