Metadata-Version: 2.1
Name: google-pandas-load
Version: 6.0.0
Summary: Wrapper for transferring data from A to B, where A and B are distinct and chosen between BigQuery, Storage, a local directory and pandas.
Home-page: UNKNOWN
Author: Augustin Barillec
Author-email: augustin.barillec@gmail.com
License: UNKNOWN
Project-URL: Documentation, https://google-pandas-load.readthedocs.io/en/latest/
Project-URL: Source, https://github.com/augustin-barillec/google-pandas-load
Platform: UNKNOWN
Classifier: Programming Language :: Python :: 3.6
Classifier: Programming Language :: Python :: 3.7
Classifier: Programming Language :: Python :: 3.8
Classifier: Programming Language :: Python :: 3.9
Classifier: Programming Language :: Python :: 3.10
Classifier: Programming Language :: Python :: 3.11
Classifier: License :: OSI Approved :: MIT License
Classifier: Operating System :: POSIX :: Linux
License-File: LICENSE
Requires-Dist: google-cloud-bigquery (==3.*)
Requires-Dist: google-cloud-storage (==2.*)
Requires-Dist: pandas (==2.*)
